interfaces/__init__.py
interfaces/boot.py
interfaces/interface.py
scheduler/__init__.py
scheduler/agentManager.py
scheduler/agent_scheduler_manager.py
scheduler/core/Thought.py
scheduler/core/__init__.py
scheduler/core/init.py
scheduler/core/RAGLibrary/RAG.py
scheduler/core/RAGLibrary/RAGL_Calc.py
scheduler/core/RAGLibrary/__init__.py
scheduler/core/RAGLibrary/exceptions/NoSuchRAGLFileException.py
scheduler/core/RAGLibrary/exceptions/__init__.py
scheduler/core/RAGLibrary/statics/.gitattributes
scheduler/core/RAGLibrary/statics/RAGL.sqlite
scheduler/core/RAGLibrary/tools/__init__.py
scheduler/core/RAGLibrary/tools/misc.py
scheduler/core/console/agent_test.py
scheduler/core/mcp_client/__init__.py
scheduler/core/mcp_client/mcp_client.py
scheduler/core/mcp_client/mcp_console.py
scheduler/core/schemas/__init__.py
scheduler/core/schemas/schemas.py
scheduler/core/schemas/structure/TRM.ipynb
scheduler/core/schemas/structure/ToT.py
scheduler/core/schemas/structure/__init__.py
scheduler/core/schemas/structure/task_relation_manager.py
scheduler/core/schemas/structure/.ipynb_checkpoints/TRM-checkpoint.ipynb
scheduler/core/schemas/structure/.ipynb_checkpoints/__init__-checkpoint.py
scheduler/core/schemas/structure/.ipynb_checkpoints/task_relation_manager-checkpoint.py
scheduler/core/schemas/works/PydanticSafetyParser.py
scheduler/core/schemas/works/__init__.py
scheduler/core/tasks/__init__.py
scheduler/core/tasks/task.py
scheduler/core/tasks/agents/__init__.py
scheduler/core/tasks/agents/console_agent.py
scheduler/core/tasks/exceptions/__init__.py
scheduler/core/tasks/exceptions/basic_task_exceptions.py
scheduler/core/tasks/exceptions/task_exceptions.py
scheduler/core/tasks/status/__init__.py
scheduler/core/tasks/status/status.py
scheduler/core/tools/__init__.py
scheduler/core/tools/agent_with_tools.py
scheduler/core/tools/common_tool.py
scheduler/toolschain/__init__.py
scheduler/toolschain/tools_manager.py
test/Untitled.ipynb
test/__init__.py
test/streaming_response.py
villager-0.1.dev54.dist-info/METADATA
villager-0.1.dev54.dist-info/WHEEL
villager-0.1.dev54.dist-info/entry_points.txt
villager-0.1.dev54.dist-info/top_level.txt
villager-0.1.dev54.dist-info/RECORD
